example_game_of_life.py
example_linear_colors.py
example_radial_gradient.py
example_visual.py
example_visual_2d.py
maximumssuche.py
pong_dev251209.py
pycessingame.py
pycessingame_bak.py
test.py
test_colors.py
test_image_functions.py
test_misc_errors.py
test_names.py
test_naming.py
test_playground.py
test_processing_2d.py
test_text_and_fonts.py
pycessingame-0.4.3.dist-info/licenses/LICENSE
pycessingame-0.4.3.dist-info/METADATA
pycessingame-0.4.3.dist-info/WHEEL
pycessingame-0.4.3.dist-info/top_level.txt
pycessingame-0.4.3.dist-info/RECORD
