Metadata-Version: 2.4
Name: pycessingame
Version: 0.4.3
Summary: PROCESSING style creative coding not only for education using PYTHON and PYGAME - PROCESSING-Style kreatives coden mit PYTHON und PYGAME für Ausbildung und Lehre
Author-email: dickschaedel <dickschaedel@example.org>
License-Expression: Unlicense
Project-URL: Homepage, https://codeberg.org/dickschaedel/pycessingame
Project-URL: Source, https://codeberg.org/dickschaedel/pycessingame
Keywords: processing,creative-coding,visual,graphics,drawing,pygame,education,learning,sketch,art,animation,p5,py5
Classifier: Programming Language :: Python :: 3
Classifier: Topic :: Multimedia :: Graphics
Classifier: Topic :: Education
Classifier: Topic :: Artistic Software
Classifier: Intended Audience :: Education
Classifier: Intended Audience :: Developers
Classifier: Intended Audience :: End Users/Desktop
Classifier: Development Status :: 3 - Alpha
Requires-Python: >=3.9
License-File: LICENSE
Requires-Dist: pygame
Dynamic: license-file
